decipher/__init__.py
decipher/cfg.yaml
decipher/cls.py
decipher/data/__init__.py
decipher/data/augment.py
decipher/data/mnn_dataset.py
decipher/data/process.py
decipher/emb.py
decipher/explain/__init__.py
decipher/explain/gene/__init__.py
decipher/explain/gene/gene_selection.py
decipher/explain/gene/lr.py
decipher/explain/gene/mixin.py
decipher/explain/regress/__init__.py
decipher/explain/regress/mixin.py
decipher/explain/regress/regression.py
decipher/graphic/__init__.py
decipher/graphic/build.py
decipher/graphic/knn.py
decipher/nn/__init__.py
decipher/nn/layers.py
decipher/nn/loss.py
decipher/nn/models/_basic.py
decipher/nn/models/sc.py
decipher/nn/models/spatial.py
decipher/utils.py
cell_decipher-0.3.2.dist-info/METADATA
cell_decipher-0.3.2.dist-info/WHEEL
cell_decipher-0.3.2.dist-info/entry_points.txt
cell_decipher-0.3.2.dist-info/licenses/LICENSE
cell_decipher-0.3.2.dist-info/RECORD
