Metadata-Version: 2.4
Name: cell-decipher
Version: 0.3.2
Summary: DECIPHER for learning disentangled cellular embeddings in large-scale heterogeneous spatial omics data
License: MIT
License-File: LICENSE
Keywords: bioinformatics,transformer,single-cell,spatial-omics,deep-learning
Author: Chen-Rui Xia
Author-email: xiachenrui@mail.cbi.pku.edu.cn
Requires-Python: >=3.10
Classifier: Intended Audience :: Science/Research
Classifier: License :: OSI Approved :: MIT License
Classifier: Natural Language :: English
Classifier: Operating System :: MacOS :: MacOS X
Classifier: Operating System :: POSIX :: Linux
Classifier: Programming Language :: Python :: 3
Classifier: Programming Language :: Python :: 3.10
Classifier: Programming Language :: Python :: 3.11
Classifier: Programming Language :: Python :: 3.12
Classifier: Programming Language :: Python :: 3.13
Classifier: Programming Language :: Python :: 3.14
Classifier: Topic :: Scientific/Engineering :: Bio-Informatics
Provides-Extra: dev
Provides-Extra: docs
Requires-Dist: black ; extra == "dev"
Requires-Dist: bs4
Requires-Dist: einops
Requires-Dist: harmony-pytorch
Requires-Dist: ipython
Requires-Dist: isort ; extra == "dev"
Requires-Dist: jinja2 ; extra == "docs"
Requires-Dist: jupyter ; extra == "dev"
Requires-Dist: jupyter_contrib_nbextensions ; extra == "dev"
Requires-Dist: jupytext ; extra == "dev"
Requires-Dist: leidenalg
Requires-Dist: loguru
Requires-Dist: myst-parser ; extra == "docs"
Requires-Dist: nbformat ; extra == "dev"
Requires-Dist: nbsphinx ; extra == "docs"
Requires-Dist: papermill ; extra == "dev"
Requires-Dist: pip
Requires-Dist: pre-commit ; extra == "dev"
Requires-Dist: py-spy ; extra == "dev"
Requires-Dist: pytest ; extra == "dev"
Requires-Dist: pytest-cov ; extra == "dev"
Requires-Dist: pytest-sugar ; extra == "dev"
Requires-Dist: pytest-xdist ; extra == "dev"
Requires-Dist: pytorch-lightning (>=2.1)
Requires-Dist: pyyaml
Requires-Dist: ray[default]
Requires-Dist: rui_utils
Requires-Dist: scanpy (>=1.9)
Requires-Dist: scikit-learn (<1.6)
Requires-Dist: scikit-misc (>=0.3)
Requires-Dist: sphinx (<=6.2.1) ; extra == "docs"
Requires-Dist: sphinx-autodoc-typehints ; extra == "docs"
Requires-Dist: sphinx-copybutton ; extra == "docs"
Requires-Dist: sphinx-intl ; extra == "docs"
Requires-Dist: sphinx-rtd-theme ; extra == "docs"
Requires-Dist: sphinx_gallery (>=0.8.2,<0.11) ; extra == "docs"
Requires-Dist: tensorboard
Requires-Dist: torch (>=2.0,<2.9)
Requires-Dist: torch_geometric (>=2.3.0)
Requires-Dist: torchaudio
Requires-Dist: torchvision
Requires-Dist: transformers
Project-URL: Documentation, https://decipher.readthedocs.io/en/latest/
Project-URL: Homepage, https://github.com/gao-lab/decipher
Project-URL: Repository, https://github.com/gao-lab/decipher
